{
  "schemaVersion": "1",
  "header": {
    "kitA": "brushfire",
    "kitB": "dummy",
    "kitAPath": "arena/fusions/brushfire-1262ed95.record.json",
    "kitBPath": "dummy",
    "seed": 1,
    "config": {
      "hpScale": 0,
      "mana": 10000,
      "amplifyMajor": 2.5
    },
    "durationSeconds": 6.900008201599121,
    "winner": "draw",
    "endReason": "quiescent",
    "entities": [
      {
        "id": 1,
        "name": "brushfire",
        "maxHp": 1600,
        "spawn": {
          "x": 0,
          "y": 0,
          "z": 0
        }
      },
      {
        "id": 2,
        "name": "dummy",
        "maxHp": 1600,
        "spawn": {
          "x": 8,
          "y": 0,
          "z": 0
        }
      }
    ],
    "mode": "showcase",
    "maxSeconds": 30
  },
  "events": [
    {
      "t": 0,
      "type": "CastStarted",
      "canonical": "cast E1 brushfire",
      "payload": {
        "caster": 1,
        "spell": "brushfire"
      }
    },
    {
      "t": 0.40000003576278687,
      "type": "CastResolved",
      "canonical": "castResolved E1 brushfire",
      "payload": {
        "caster": 1,
        "spell": "brushfire"
      }
    },
    {
      "t": 0.40000003576278687,
      "type": "DamageDealt",
      "canonical": "damage E2 amt=89.6 Fire crit=False killed=False absorbed=0",
      "payload": {
        "target": 2,
        "amount": 89.5999984741211,
        "element": "Fire",
        "crit": false,
        "killed": false,
        "absorbed": 0,
        "evaded": false
      }
    },
    {
      "t": 0.40000003576278687,
      "type": "ZoneSpawned",
      "canonical": "zoneSpawned Z1 Circle r=10 dur=5",
      "payload": {
        "id": 1,
        "center": {
          "x": 8,
          "y": 0,
          "z": 0
        },
        "shape": "Circle",
        "size": 10,
        "duration": 5
      }
    },
    {
      "t": 0.9000001549720764,
      "type": "ZoneTicked",
      "canonical": "zoneTick Z1 affected=1",
      "payload": {
        "id": 1,
        "affected": 1
      }
    },
    {
      "t": 0.9000001549720764,
      "type": "DamageDealt",
      "canonical": "damage E2 amt=64 Fire crit=False killed=False absorbed=0",
      "payload": {
        "target": 2,
        "amount": 64,
        "element": "Fire",
        "crit": false,
        "killed": false,
        "absorbed": 0,
        "evaded": false
      }
    },
    {
      "t": 0.9000001549720764,
      "type": "StatusApplied",
      "canonical": "status E2 Burn dur=2 stacks=1 refreshed=False",
      "payload": {
        "target": 2,
        "status": "Burn",
        "duration": 2,
        "stacks": 1,
        "resisted": false,
        "refreshed": false
      }
    },
    {
      "t": 0.9000001549720764,
      "type": "StatusApplied",
      "canonical": "status E2 Root dur=2 stacks=1 refreshed=False",
      "payload": {
        "target": 2,
        "status": "Root",
        "duration": 2,
        "stacks": 1,
        "resisted": false,
        "refreshed": false
      }
    },
    {
      "t": 1.399999737739563,
      "type": "ZoneTicked",
      "canonical": "zoneTick Z1 affected=1",
      "payload": {
        "id": 1,
        "affected": 1
      }
    },
    {
      "t": 1.399999737739563,
      "type": "DamageDealt",
      "canonical": "damage E2 amt=64 Fire crit=False killed=False absorbed=0",
      "payload": {
        "target": 2,
        "amount": 64,
        "element": "Fire",
        "crit": false,
        "killed": false,
        "absorbed": 0,
        "evaded": false
      }
    },
    {
      "t": 1.399999737739563,
      "type": "StatusApplied",
      "canonical": "status E2 Burn dur=2 stacks=2 refreshed=True",
      "payload": {
        "target": 2,
        "status": "Burn",
        "duration": 2,
        "stacks": 2,
        "resisted": false,
        "refreshed": true
      }
    },
    {
      "t": 1.399999737739563,
      "type": "StatusApplied",
      "canonical": "status E2 Root dur=1 stacks=1 refreshed=True",
      "payload": {
        "target": 2,
        "status": "Root",
        "duration": 1,
        "stacks": 1,
        "resisted": false,
        "refreshed": true
      }
    },
    {
      "t": 1.399999737739563,
      "type": "DamageDealt",
      "canonical": "damage E2 amt=102.4 Fire crit=False killed=False absorbed=0",
      "payload": {
        "target": 2,
        "amount": 102.4000015258789,
        "element": "Fire",
        "crit": false,
        "killed": false,
        "absorbed": 0,
        "evaded": false
      }
    },
    {
      "t": 1.8999992609024048,
      "type": "ZoneTicked",
      "canonical": "zoneTick Z1 affected=1",
      "payload": {
        "id": 1,
        "affected": 1
      }
    },
    {
      "t": 1.8999992609024048,
      "type": "DamageDealt",
      "canonical": "damage E2 amt=64 Fire crit=False killed=False absorbed=0",
      "payload": {
        "target": 2,
        "amount": 64,
        "element": "Fire",
        "crit": false,
        "killed": false,
        "absorbed": 0,
        "evaded": false
      }
    },
    {
      "t": 1.8999992609024048,
      "type": "StatusApplied",
      "canonical": "status E2 Burn dur=2 stacks=3 refreshed=True",
      "payload": {
        "target": 2,
        "status": "Burn",
        "duration": 2,
        "stacks": 3,
        "resisted": false,
        "refreshed": true
      }
    },
    {
      "t": 1.8999992609024048,
      "type": "StatusApplied",
      "canonical": "status E2 Root dur=0.5 stacks=1 refreshed=True",
      "payload": {
        "target": 2,
        "status": "Root",
        "duration": 0.5,
        "stacks": 1,
        "resisted": false,
        "refreshed": true
      }
    },
    {
      "t": 1.8999992609024048,
      "type": "DamageDealt",
      "canonical": "damage E2 amt=153.6 Fire crit=False killed=False absorbed=0",
      "payload": {
        "target": 2,
        "amount": 153.60000610351562,
        "element": "Fire",
        "crit": false,
        "killed": false,
        "absorbed": 0,
        "evaded": false
      }
    },
    {
      "t": 2.399998903274536,
      "type": "ZoneTicked",
      "canonical": "zoneTick Z1 affected=1",
      "payload": {
        "id": 1,
        "affected": 1
      }
    },
    {
      "t": 2.399998903274536,
      "type": "DamageDealt",
      "canonical": "damage E2 amt=64 Fire crit=False killed=False absorbed=0",
      "payload": {
        "target": 2,
        "amount": 64,
        "element": "Fire",
        "crit": false,
        "killed": false,
        "absorbed": 0,
        "evaded": false
      }
    },
    {
      "t": 2.399998903274536,
      "type": "StatusApplied",
      "canonical": "status E2 Burn dur=2 stacks=4 refreshed=True",
      "payload": {
        "target": 2,
        "status": "Burn",
        "duration": 2,
        "stacks": 4,
        "resisted": false,
        "refreshed": true
      }
    },
    {
      "t": 2.399998903274536,
      "type": "StatusApplied",
      "canonical": "status E2 Root resisted",
      "payload": {
        "target": 2,
        "status": "Root",
        "duration": 0,
        "stacks": 0,
        "resisted": true,
        "refreshed": false
      }
    },
    {
      "t": 2.399998903274536,
      "type": "DamageDealt",
      "canonical": "damage E2 amt=204.8 Fire crit=False killed=False absorbed=0",
      "payload": {
        "target": 2,
        "amount": 204.8000030517578,
        "element": "Fire",
        "crit": false,
        "killed": false,
        "absorbed": 0,
        "evaded": false
      }
    },
    {
      "t": 2.399998903274536,
      "type": "StatusRemoved",
      "canonical": "statusRemoved E2 Root",
      "payload": {
        "target": 2,
        "status": "Root"
      }
    },
    {
      "t": 2.899998426437378,
      "type": "ZoneTicked",
      "canonical": "zoneTick Z1 affected=1",
      "payload": {
        "id": 1,
        "affected": 1
      }
    },
    {
      "t": 2.899998426437378,
      "type": "DamageDealt",
      "canonical": "damage E2 amt=64 Fire crit=False killed=False absorbed=0",
      "payload": {
        "target": 2,
        "amount": 64,
        "element": "Fire",
        "crit": false,
        "killed": false,
        "absorbed": 0,
        "evaded": false
      }
    },
    {
      "t": 2.899998426437378,
      "type": "StatusApplied",
      "canonical": "status E2 Burn dur=2 stacks=5 refreshed=True",
      "payload": {
        "target": 2,
        "status": "Burn",
        "duration": 2,
        "stacks": 5,
        "resisted": false,
        "refreshed": true
      }
    },
    {
      "t": 2.899998426437378,
      "type": "StatusApplied",
      "canonical": "status E2 Root resisted",
      "payload": {
        "target": 2,
        "status": "Root",
        "duration": 0,
        "stacks": 0,
        "resisted": true,
        "refreshed": false
      }
    },
    {
      "t": 2.899998426437378,
      "type": "DamageDealt",
      "canonical": "damage E2 amt=256 Fire crit=False killed=False absorbed=0",
      "payload": {
        "target": 2,
        "amount": 256,
        "element": "Fire",
        "crit": false,
        "killed": false,
        "absorbed": 0,
        "evaded": false
      }
    },
    {
      "t": 3.3999979496002197,
      "type": "ZoneTicked",
      "canonical": "zoneTick Z1 affected=1",
      "payload": {
        "id": 1,
        "affected": 1
      }
    },
    {
      "t": 3.3999979496002197,
      "type": "DamageDealt",
      "canonical": "damage E2 amt=64 Fire crit=False killed=False absorbed=0",
      "payload": {
        "target": 2,
        "amount": 64,
        "element": "Fire",
        "crit": false,
        "killed": false,
        "absorbed": 0,
        "evaded": false
      }
    },
    {
      "t": 3.3999979496002197,
      "type": "StatusApplied",
      "canonical": "status E2 Burn dur=2 stacks=5 refreshed=True",
      "payload": {
        "target": 2,
        "status": "Burn",
        "duration": 2,
        "stacks": 5,
        "resisted": false,
        "refreshed": true
      }
    },
    {
      "t": 3.3999979496002197,
      "type": "StatusApplied",
      "canonical": "status E2 Root resisted",
      "payload": {
        "target": 2,
        "status": "Root",
        "duration": 0,
        "stacks": 0,
        "resisted": true,
        "refreshed": false
      }
    },
    {
      "t": 3.3999979496002197,
      "type": "DamageDealt",
      "canonical": "damage E2 amt=256 Fire crit=False killed=False absorbed=0",
      "payload": {
        "target": 2,
        "amount": 256,
        "element": "Fire",
        "crit": false,
        "killed": false,
        "absorbed": 0,
        "evaded": false
      }
    },
    {
      "t": 3.8999974727630615,
      "type": "ZoneTicked",
      "canonical": "zoneTick Z1 affected=1",
      "payload": {
        "id": 1,
        "affected": 1
      }
    },
    {
      "t": 3.8999974727630615,
      "type": "DamageDealt",
      "canonical": "damage E2 amt=64 Fire crit=False killed=False absorbed=0",
      "payload": {
        "target": 2,
        "amount": 64,
        "element": "Fire",
        "crit": false,
        "killed": false,
        "absorbed": 0,
        "evaded": false
      }
    },
    {
      "t": 3.8999974727630615,
      "type": "StatusApplied",
      "canonical": "status E2 Burn dur=2 stacks=5 refreshed=True",
      "payload": {
        "target": 2,
        "status": "Burn",
        "duration": 2,
        "stacks": 5,
        "resisted": false,
        "refreshed": true
      }
    },
    {
      "t": 3.8999974727630615,
      "type": "StatusApplied",
      "canonical": "status E2 Root resisted",
      "payload": {
        "target": 2,
        "status": "Root",
        "duration": 0,
        "stacks": 0,
        "resisted": true,
        "refreshed": false
      }
    },
    {
      "t": 3.8999974727630615,
      "type": "DamageDealt",
      "canonical": "damage E2 amt=256 Fire crit=False killed=True absorbed=0",
      "payload": {
        "target": 2,
        "amount": 256,
        "element": "Fire",
        "crit": false,
        "killed": true,
        "absorbed": 0,
        "evaded": false
      }
    },
    {
      "t": 4.399998664855957,
      "type": "ZoneTicked",
      "canonical": "zoneTick Z1 affected=0",
      "payload": {
        "id": 1,
        "affected": 0
      }
    },
    {
      "t": 4.90000057220459,
      "type": "ZoneTicked",
      "canonical": "zoneTick Z1 affected=0",
      "payload": {
        "id": 1,
        "affected": 0
      }
    },
    {
      "t": 5.400002479553223,
      "type": "ZoneTicked",
      "canonical": "zoneTick Z1 affected=0",
      "payload": {
        "id": 1,
        "affected": 0
      }
    },
    {
      "t": 5.400002479553223,
      "type": "ZoneExpired",
      "canonical": "zoneExpired Z1",
      "payload": {
        "id": 1
      }
    },
    {
      "t": 5.9000043869018555,
      "type": "StatusRemoved",
      "canonical": "statusRemoved E2 Burn",
      "payload": {
        "target": 2,
        "status": "Burn"
      }
    }
  ]
}